README.md
setup.py
mem_agent.egg-info/PKG-INFO
mem_agent.egg-info/SOURCES.txt
mem_agent.egg-info/dependency_links.txt
mem_agent.egg-info/requires.txt
mem_agent.egg-info/top_level.txt
vector_stores/__init__.py
vector_stores/base.py
vector_stores/configs.py
vector_stores/qdrant.py